<PAMDataset>
  <PAMRasterBand band="1">
    <Description>EucDist_stre1</Description>
    <Histograms>
      <HistItem>
        <HistMin>0</HistMin>
        <HistMax>684.105224609375</HistMax>
        <BucketCount>256</BucketCount>
        <IncludeOutOfRange>1</IncludeOutOfRange>
        <Approximate>0</Approximate>
        <HistCounts>34968|0|0|0|0|0|0|0|0|0|0|64168|0|0|0|25254|0|0|0|0|0|0|34962|0|0|25758|0|0|0|0|0|20715|0|21451|0|13944|0|0|0|0|21005|0|0|0|17967|0|12039|9652|0|0|11260|0|0|0|0|28039|0|8038|0|0|9406|0|0|7403|0|8842|0|9223|6809|0|7833|8326|0|0|0|7194|0|0|7317|10136|5439|5093|0|0|0|5780|0|6118|0|5241|8595|0|4070|0|3164|4159|3432|0|0|0|7486|3073|0|6680|0|2935|2741|0|0|0|4796|4448|2092|0|2074|2108|1927|0|2209|0|3465|0|0|2811|0|2822|916|2392|0|0|2248|0|0|0|2850|899|1524|0|733|0|735|654|407|542|0|2025|0|432|0|441|796|0|678|0|0|625|434|0|552|0|395|164|174|0|0|157|275|176|91|93|182|81|0|126|60|71|113|0|29|42|134|0|71|30|37|37|26|35|0|13|73|40|12|17|0|53|0|15|17|10|15|32|8|0|10|26|14|0|12|0|13|0|10|5|3|11|0|3|0|1|7|1|1|1|0|2|4|0|0|0|5|0|1|1|0|3|1|0|0|1|2|1|0|0|0|2|0|0|1|0|1|0|0|0|0|1</HistCounts>
      </HistItem>
    </Histograms>
  </PAMRasterBand>
</PAMDataset>
